<?xml version='1.0' encoding='utf-8'?>
<TextureAtlas imagePath="MicUpBF.png">
<SubTexture name="idle0000" x="3954" y="3763" width="1993" height="1755" frameX="-58" frameY="-411" frameWidth="2448" frameHeight="2448" />
<SubTexture name="idle0001" x="3954" y="3763" width="1993" height="1755" frameX="-58" frameY="-411" frameWidth="2448" frameHeight="2448" />
<SubTexture name="idle0002" x="1874" y="1970" width="1985" height="1759" frameX="-55" frameY="-409" frameWidth="2448" frameHeight="2448" />
<SubTexture name="idle0003" x="1874" y="1970" width="1985" height="1759" frameX="-55" frameY="-409" frameWidth="2448" frameHeight="2448" />
<SubTexture name="idle0004" x="5478" y="0" width="1970" height="1758" frameX="-73" frameY="-409" frameWidth="2448" frameHeight="2448" />
<SubTexture name="idle0005" x="5478" y="0" width="1970" height="1758" frameX="-73" frameY="-409" frameWidth="2448" frameHeight="2448" />
<SubTexture name="idle0006" x="0" y="3763" width="1975" height="1757" frameX="-66" frameY="-410" frameWidth="2448" frameHeight="2448" />
<SubTexture name="idle0007" x="0" y="3763" width="1975" height="1757" frameX="-66" frameY="-410" frameWidth="2448" frameHeight="2448" />
<SubTexture name="idle0008" x="1975" y="3763" width="1979" height="1757" frameX="-60" frameY="-410" frameWidth="2448" frameHeight="2448" />
<SubTexture name="idle0009" x="1975" y="3763" width="1979" height="1757" frameX="-60" frameY="-410" frameWidth="2448" frameHeight="2448" />
<SubTexture name="singLEFT0000" x="5435" y="5520" width="1960" height="1695" frameX="-79" frameY="-411" frameWidth="2448" frameHeight="2448" />
<SubTexture name="singLEFT0001" x="5435" y="5520" width="1960" height="1695" frameX="-79" frameY="-411" frameWidth="2448" frameHeight="2448" />
<SubTexture name="singLEFT0002" x="1765" y="5520" width="1986" height="1697" frameX="-53" frameY="-410" frameWidth="2448" frameHeight="2448" />
<SubTexture name="singLEFT0003" x="1765" y="5520" width="1986" height="1697" frameX="-53" frameY="-410" frameWidth="2448" frameHeight="2448" />
<SubTexture name="singLEFTmiss0000" x="3751" y="5520" width="1684" height="1697" frameX="-354" frameY="-411" frameWidth="2448" frameHeight="2448" />
<SubTexture name="singLEFTmiss0001" x="3751" y="5520" width="1684" height="1697" frameX="-354" frameY="-411" frameWidth="2448" frameHeight="2448" />
<SubTexture name="singDOWN0000" x="5478" y="1758" width="1779" height="1719" frameX="-262" frameY="-411" frameWidth="2448" frameHeight="2448" />
<SubTexture name="singDOWN0001" x="5478" y="1758" width="1779" height="1719" frameX="-262" frameY="-411" frameWidth="2448" frameHeight="2448" />
<SubTexture name="singDOWN0002" x="0" y="5520" width="1765" height="1717" frameX="-275" frameY="-412" frameWidth="2448" frameHeight="2448" />
<SubTexture name="singDOWN0003" x="0" y="5520" width="1765" height="1717" frameX="-275" frameY="-412" frameWidth="2448" frameHeight="2448" />
<SubTexture name="singDOWNmiss0000" x="3751" y="5520" width="1684" height="1697" frameX="-354" frameY="-411" frameWidth="2448" frameHeight="2448" />
<SubTexture name="singDOWNmiss0001" x="3751" y="5520" width="1684" height="1697" frameX="-354" frameY="-411" frameWidth="2448" frameHeight="2448" />
<SubTexture name="singUP0000" x="0" y="1970" width="1874" height="1793" frameX="-192" frameY="-410" frameWidth="2448" frameHeight="2448" />
<SubTexture name="singUP0001" x="0" y="1970" width="1874" height="1793" frameX="-192" frameY="-410" frameWidth="2448" frameHeight="2448" />
<SubTexture name="singUP0002" x="3607" y="0" width="1871" height="1830" frameX="-218" frameY="-407" frameWidth="2448" frameHeight="2448" />
<SubTexture name="singUP0003" x="3607" y="0" width="1871" height="1830" frameX="-218" frameY="-407" frameWidth="2448" frameHeight="2448" />
<SubTexture name="singUPmiss0000" x="3751" y="5520" width="1684" height="1697" frameX="-354" frameY="-411" frameWidth="2448" frameHeight="2448" />
<SubTexture name="singUPmiss0001" x="3751" y="5520" width="1684" height="1697" frameX="-354" frameY="-411" frameWidth="2448" frameHeight="2448" />
<SubTexture name="singRIGHT0000" x="1800" y="0" width="1807" height="1966" frameX="-360" frameY="-414" frameWidth="2448" frameHeight="2448" />
<SubTexture name="singRIGHT0001" x="1800" y="0" width="1807" height="1966" frameX="-360" frameY="-414" frameWidth="2448" frameHeight="2448" />
<SubTexture name="singRIGHT0002" x="0" y="0" width="1800" height="1970" frameX="-342" frameY="-417" frameWidth="2448" frameHeight="2448" />
<SubTexture name="singRIGHT0003" x="0" y="0" width="1800" height="1970" frameX="-342" frameY="-417" frameWidth="2448" frameHeight="2448" />
<SubTexture name="singRIGHTmiss0000" x="3751" y="5520" width="1684" height="1697" frameX="-354" frameY="-411" frameWidth="2448" frameHeight="2448" />
<SubTexture name="singRIGHTmiss0001" x="3751" y="5520" width="1684" height="1697" frameX="-354" frameY="-411" frameWidth="2448" frameHeight="2448" />
</TextureAtlas>
